zoom_client/__init__.py
zoom_client/client.py
zoom_client/modules/dashboard.py
zoom_client/modules/group.py
zoom_client/modules/report.py
zoom_client/modules/users.py
zoom_client-0.0.5.dist-info/LICENSE
zoom_client-0.0.5.dist-info/METADATA
zoom_client-0.0.5.dist-info/WHEEL
zoom_client-0.0.5.dist-info/top_level.txt
zoom_client-0.0.5.dist-info/RECORD
