Metadata-Version: 2.1
Name: zoom-client
Version: 0.0.5
Summary: Zoom (Video Communications) API Client
Home-page: UNKNOWN
Author: CU Boulder, OIT
Author-email: dabu5788@colorado.edu
License: MIT
Keywords: zoom api requests
Platform: UNKNOWN
Classifier: License :: OSI Approved :: MIT License
Classifier: Operating System :: OS Independent
Requires-Python: >=3.6
Requires-Dist: bandit
Requires-Dist: black
Requires-Dist: PyJWT
Requires-Dist: pylint
Requires-Dist: pytest
Requires-Dist: ratelimit
Requires-Dist: requests
